{"@id":"https://example.com/myFeed3/registration/qml.net/0.3.0-alpha.20.json","@type":["Package","http://schema.nuget.org/catalog#Permalink"],"catalogEntry":"https://example.com/myFeed3/virtualcatalog/data/7b6c9db0-4709-4f50-b83f-d6f514e7b841.json","listed":true,"packageContent":"https://example.com/myFeed3/flatcontainer/qml.net/0.3.0-alpha.20/qml.net.0.3.0-alpha.20.nupkg","published":"2018-08-08T06:58:11.7742450Z","registration":"https://example.com/myFeed3/registration/qml.net/index.json","sleet:catalogEntry":{"@id":"https://example.com/myFeed3/virtualcatalog/data/7b6c9db0-4709-4f50-b83f-d6f514e7b841.json","@type":["PackageDetails","catalog:Permalink"],"authors":"Paul Knopf","commitId":"40df8d9e-5f30-458b-a285-46f5c007257d","commitTimeStamp":"2018-08-08T06:58:11.7807300Z","copyright":"2018","created":"2018-08-08T06:58:11.7742450Z","description":"A cross-platform Qml/.NET integration for Mono/.NET/.NET Core","iconUrl":"","id":"Qml.Net","isPrerelease":true,"language":"","lastEdited":"0001-01-01T00:00:00Z","licenseNames":"","licenseReportUrl":"","licenseUrl":"https://github.com/pauldotknopf/Qml.Net/blob/master/LICENSE","listed":true,"owners":"Paul Knopf","packageContent":"https://example.com/myFeed3/flatcontainer/qml.net/0.3.0-alpha.20/qml.net.0.3.0-alpha.20.nupkg","packageHash":"n7JvlbKKTdH6WyGdNd9raaLqI1/U3aFslOLzbf1NVFQkmHNDlN+TcZ+JRK8lE/tojj4fqVjq0cM8t/9bnuuiDA==","packageHashAlgorithm":"SHA512","packageSize":36815,"projectUrl":"https://github.com/pauldotknopf/Qml.Net","published":"2018-08-08T06:58:11.7742450Z","releaseNotes":"","requireLicenseAcceptance":false,"sleet:operation":"add","sleet:toolVersion":"2.3.33","summary":"","version":"0.3.0-alpha.20","dependencyGroups":[{"@id":"https://example.com/myFeed3/virtualcatalog/data/7b6c9db0-4709-4f50-b83f-d6f514e7b841.json#dependencygroup/netstandard2.0","@type":"PackageDependencyGroup","targetFramework":"netstandard2.0","dependencies":[{"@id":"https://example.com/myFeed3/virtualcatalog/data/7b6c9db0-4709-4f50-b83f-d6f514e7b841.json#dependencygroup/netstandard2.0/advanceddlsupport","@type":"PackageDependency","id":"AdvancedDLSupport","range":"[2.1.0, )"}]}],"frameworkAssemblyGroup":[],"tags":[],"@context":{"@vocab":"http://schema.nuget.org/schema#","catalog":"http://schema.nuget.org/catalog#","xsd":"http://www.w3.org/2001/XMLSchema#","sleet":"http://schema.emgarten.com/sleet#","dependencies":{"@id":"dependency","@container":"@set"},"dependencyGroups":{"@id":"dependencyGroup","@container":"@set"},"packageEntries":{"@id":"packageEntry","@container":"@set"},"supportedFrameworks":{"@id":"supportedFramework","@container":"@set"},"tags":{"@id":"tag","@container":"@set"},"published":{"@type":"xsd:dateTime"},"created":{"@type":"xsd:dateTime"},"lastEdited":{"@type":"xsd:dateTime"},"catalog:commitTimeStamp":{"@type":"xsd:dateTime"}}},"@context":{"@vocab":"http://schema.nuget.org/schema#","catalog":"http://schema.nuget.org/catalog#","xsd":"http://www.w3.org/2001/XMLSchema#","sleet":"http://schema.emgarten.com/sleet#","catalogEntry":{"@type":"@id"},"registration":{"@type":"@id"},"packageContent":{"@type":"@id"},"published":{"@type":"xsd:dateTime"},"dependencies":{"@id":"dependency","@container":"@set"},"dependencyGroups":{"@id":"dependencyGroup","@container":"@set"},"packageEntries":{"@id":"packageEntry","@container":"@set"},"supportedFrameworks":{"@id":"supportedFramework","@container":"@set"},"tags":{"@id":"tag","@container":"@set"},"created":{"@type":"xsd:dateTime"},"lastEdited":{"@type":"xsd:dateTime"},"catalog:commitTimeStamp":{"@type":"xsd:dateTime"}}}